{
  "HALProvider": {
    "Addressable LEDs": {
      "window": {
        "visible": true
      }
    },
    "Other Devices": {
      "SPARK MAX [2]": {
        "header": {
          "open": true
        }
      },
      "SPARK MAX [4]": {
        "header": {
          "open": true
        }
      },
      "Talon FX (v6)[3]": {
        "header": {
          "open": true
        }
      }
    },
    "RoboRIO": {
      "5V Rail": {
        "open": true
      },
      "6V Rail": {
        "open": true
      },
      "RoboRIO Input": {
        "open": true
      },
      "window": {
        "visible": true
      }
    }
  },
  "NTProvider": {
    "types": {
      "/FMSInfo": "FMSInfo",
      "/Shuffleboard/AmpMech/Arm PID": "PIDController",
      "/Shuffleboard/AmpMech/Claw Intake": "PIDController",
      "/Shuffleboard/AmpMech/Claw Intake Reset Claw Encoder": "Command",
      "/Shuffleboard/AmpMech/Elevator Reset Encoder": "Command",
      "/Shuffleboard/AmpMech/Elevator/ Elev PID": "PIDController",
      "/Shuffleboard/AmpMech/Reset Arm Encoder": "Command",
      "/Shuffleboard/AmpMechElevator/Elev PID": "PIDController",
      "/Shuffleboard/AmpMechElevator/Elevator Reset Encoder": "Command",
      "/Shuffleboard/Climb/PID": "PIDController",
      "/Shuffleboard/Climb/Reset Encoder": "Command",
      "/Shuffleboard/Intake/Drop PID": "PIDController",
      "/Shuffleboard/Intake/Reset Intake Drop Encoder": "Command",
      "/Shuffleboard/Intake/Reset Intake Wheel Encoder": "Command",
      "/Shuffleboard/Intake/Wheel PID": "PIDController",
      "/Shuffleboard/Misc/Auto Chooser": "String Chooser",
      "/Shuffleboard/SwerveDrive/Field": "Field2d",
      "/SmartDashboard/Field": "Field2d"
    },
    "windows": {
      "/FMSInfo": {
        "window": {
          "visible": true
        }
      },
      "/Shuffleboard/Climb/PID": {
        "window": {
          "visible": true
        }
      }
    }
  },
  "NetworkTables": {
    "retained": {
      "Shuffleboard": {
        "SwerveDrive": {
          "open": true
        },
        "open": true
      }
    },
    "transitory": {
      "FMSInfo": {
        "open": true
      },
      "Shuffleboard": {
        "open": true
      }
    }
  },
  "NetworkTables Info": {
    "visible": true
  }
}
